rofi_tmuxp/__init__.py
rofi_tmuxp/cli.py
rofi_tmuxp/rofi_client.py
rofi_tmuxp/sessions.py
rofi_tmuxp/tmuxp_client.py
rofi_tmuxp-0.6.0.dist-info/entry_points.txt
rofi_tmuxp-0.6.0.dist-info/LICENSE
rofi_tmuxp-0.6.0.dist-info/WHEEL
rofi_tmuxp-0.6.0.dist-info/METADATA
rofi_tmuxp-0.6.0.dist-info/RECORD
