Metadata-Version: 2.1
Name: rofi-tmuxp
Version: 0.6.0
Summary: Rofi script to launch tmuxp sessions.
Keywords: rofi,tmux,tmuxp
Author-email: Heinrich Kruger <heindsight@kruger.dev>
Requires-Python: ~=3.8
Classifier: Development Status :: 4 - Beta
Classifier: Intended Audience :: End Users/Desktop
Classifier: License :: OSI Approved :: MIT License
Classifier: Topic :: Desktop Environment :: Window Managers
Classifier: Programming Language :: Python :: 3
Classifier: Programming Language :: Python :: 3.8
Classifier: Programming Language :: Python :: 3.9
Classifier: Programming Language :: Python :: 3.10
Classifier: Programming Language :: Python :: 3.11
Classifier: Programming Language :: Python :: 3.12
Requires-Dist: pyyaml
Requires-Dist: tmuxp ~= 1.1
Requires-Dist: black ; extra == "dev"
Requires-Dist: docformatter ; extra == "dev"
Requires-Dist: flake8 ; extra == "dev"
Requires-Dist: flake8-pyproject ; extra == "dev"
Requires-Dist: flake8-pytest-style ; extra == "dev"
Requires-Dist: isort ; extra == "dev"
Requires-Dist: mypy ; extra == "dev"
Requires-Dist: pdbpp ; extra == "dev"
Requires-Dist: pytest ; extra == "dev"
Requires-Dist: pytest-cov ; extra == "dev"
Requires-Dist: pytest-mock ; extra == "dev"
Requires-Dist: pytest-randomly ; extra == "dev"
Requires-Dist: rstcheck ; extra == "dev"
Requires-Dist: types-pyyaml ; extra == "dev"
Project-URL: Homepage, https://github.com/heindsight/rofi-tmuxp
Provides-Extra: dev
